limes_x/__init__.py
limes_x/__main__.py
limes_x/cli.py
limes_x/telemetry.py
limes_x/version.txt
limes_x/workflow.py
limes_x/common/__init__.py
limes_x/common/utils.py
limes_x/environments/__init__.py
limes_x/environments/_setup.py
limes_x/environments/hpc.py
limes_x/environments/local.py
limes_x/execution/__init__.py
limes_x/execution/comms.py
limes_x/execution/executors.py
limes_x/execution/instances.py
limes_x/execution/modules.py
limes_x/execution/solver.py
limes_x/execution/template_module_definition.py
limes_x/presets/__init__.py
limes_x/presets/slurm.py
limes_x-1.1.8.dist-info/METADATA
limes_x-1.1.8.dist-info/WHEEL
limes_x-1.1.8.dist-info/entry_points.txt
limes_x-1.1.8.dist-info/top_level.txt
limes_x-1.1.8.dist-info/RECORD
