Metadata-Version: 2.1
Name: limes-x
Version: 1.1.8
Summary: declarative workflow automation
Home-page: https://github.com/hallamlab/limes-x
Author: Tony Liu
Author-email: contacttonyliu@gmail.com
Project-URL: Bug Tracker, https://github.com/hallamlab/limes-x/issues
Classifier: Programming Language :: Python :: 3
Classifier: Operating System :: OS Independent
Requires-Python: >=3.10
Requires-Dist: snakemake
